pyfwapi/__init__.py
pyfwapi/apiconnection.py
pyfwapi/errors.py
pyfwapi/log.py
pyfwapi/py.typed
pyfwapi/tenant.py
pyfwapi/change/__init__.py
pyfwapi/change/manager.py
pyfwapi/change/stateful.py
pyfwapi/model/__init__.py
pyfwapi/model/asset.py
pyfwapi/model/background_tasks.py
pyfwapi/model/basemodel.py
pyfwapi/model/collection.py
pyfwapi/model/instance_info.py
pyfwapi/model/paged.py
pyfwapi/model/preview_rendition.py
pyfwapi/model/upload_request.py
pyfwapi/search/__init__.py
pyfwapi/search/ast.py
pyfwapi/search/predicates.py
pyfwapi/search/search_expression.py
pyfwapi/util/alist.py
pyfwapi-0.2.8.dist-info/METADATA
pyfwapi-0.2.8.dist-info/WHEEL
pyfwapi-0.2.8.dist-info/RECORD
