Metadata-Version: 2.4
Name: pyfwapi
Version: 0.2.8
Summary: Work with the Fotoware API in Python
Author-email: Redmer Kronemeijer <12477216+redmer@users.noreply.github.com>
License-Expression: MPL-2.0
Requires-Python: >=3.12
Requires-Dist: aiolimiter>=1.2.1
Requires-Dist: aiostream>=0.6.4
Requires-Dist: authlib>=1.4.1
Requires-Dist: httpx>=0.28.1
Requires-Dist: pydantic>=2.10.6
